cppmaked/__main__.py
cppmaked-127.0.14.dist-info/METADATA
cppmaked-127.0.14.dist-info/WHEEL
cppmaked-127.0.14.dist-info/entry_points.txt
cppmaked-127.0.14.dist-info/top_level.txt
cppmaked-127.0.14.dist-info/RECORD
