Metadata-Version: 2.4
Name: cppmaked
Version: 127.0.14
Summary: A modern C++ builder based on C++20 Modules.
Author-email: shyeyian <shyeyian@icloud.com>
License-Expression: MIT
Requires-Python: >=3.13
Requires-Dist: cppmakelib
